{
  "version": "https://jsonfeed.org/version/1",
  "title": "📷 Goldfinch — https://photos.rgrannell.xyz",
  "home_page_url": "https://photos.rgrannell.xyz",
  "feed_url": "https://photos.rgrannell.xyz/feeds/Goldfinch.json",
  "description": "📷 Goldfinch — photos.rgrannell.xyz",
  "icon": "https://photos.rgrannell.xyz/icons/android-chrome-512x512.png",
  "favicon": "https://photos.rgrannell.xyz/favicon.ico",
  "author": {
    "name": "R* Grannell",
    "url": "https://rgrannell.xyz",
    "avatar": "https://rgrannell.xyz/me.png"
  },
  "language": "en-IE",
  "items": [
    {
      "id": "https://xyz-rgrannell-photos.ams3.cdn.digitaloceanspaces.com/20d08d590848e438cceb8a457373b6105f160581fefd6047c5c8cb2dea9d6ffe.webp",
      "url": "https://xyz-rgrannell-photos.ams3.cdn.digitaloceanspaces.com/20d08d590848e438cceb8a457373b6105f160581fefd6047c5c8cb2dea9d6ffe.webp",
      "image": "https://xyz-rgrannell-photos.ams3.cdn.digitaloceanspaces.com/0168f1caa5961502b42ec0664bac25fef3456d951bc1a23df9381da595218f61_thumbnail.webp",
      "date_published": "2023-04-10T08:41:43Z",
      "content_html": "<img src='https://xyz-rgrannell-photos.ams3.cdn.digitaloceanspaces.com/0168f1caa5961502b42ec0664bac25fef3456d951bc1a23df9381da595218f61_thumbnail.webp' alt='Photo'>"
    }
  ]
}
