{
  "version": "https://jsonfeed.org/version/1",
  "title": "📷 Lake Geneva — https://photos.rgrannell.xyz",
  "home_page_url": "https://photos.rgrannell.xyz",
  "feed_url": "https://photos.rgrannell.xyz/feeds/Lake Geneva.json",
  "description": "📷 Lake Geneva — photos.rgrannell.xyz",
  "icon": "https://photos.rgrannell.xyz/icons/android-chrome-512x512.png",
  "favicon": "https://photos.rgrannell.xyz/favicon.ico",
  "author": {
    "name": "R* Grannell",
    "url": "https://rgrannell.xyz",
    "avatar": "https://rgrannell.xyz/me.png"
  },
  "language": "en-IE",
  "items": [
    {
      "id": "https://xyz-rgrannell-photos.ams3.cdn.digitaloceanspaces.com/59c72fc1dcc1e1864ba106dbd8d496efca2cc7bf062de2a2b5ecd2604764726b.webp",
      "url": "https://xyz-rgrannell-photos.ams3.cdn.digitaloceanspaces.com/59c72fc1dcc1e1864ba106dbd8d496efca2cc7bf062de2a2b5ecd2604764726b.webp",
      "image": "https://xyz-rgrannell-photos.ams3.cdn.digitaloceanspaces.com/d91642c6544b2d92ac750fe74a1b015f0b88f0d116fc162fb57a52f889da4e89_thumbnail.webp",
      "date_published": "2022-07-29T23:04:23Z",
      "content_html": "<img src='https://xyz-rgrannell-photos.ams3.cdn.digitaloceanspaces.com/d91642c6544b2d92ac750fe74a1b015f0b88f0d116fc162fb57a52f889da4e89_thumbnail.webp' alt='Photo'>"
    }
  ]
}